solarium/__init__.py
solarium/__main__.py
solarium/led.py
solarium/player.py
solarium/utils.py
solarium-0.4.3.dist-info/LICENSE
solarium-0.4.3.dist-info/METADATA
solarium-0.4.3.dist-info/WHEEL
solarium-0.4.3.dist-info/entry_points.txt
solarium-0.4.3.dist-info/top_level.txt
solarium-0.4.3.dist-info/RECORD
