Metadata-Version: 2.1
Name: solarium
Version: 0.4.3
Summary: RaspberryPi based LED controller for artificial sunlight
Home-page: https://github.com/codingjoe/solarium
Author: Johannes Maron
Author-email: info@johanneshoppe.com
License: MIT
Keywords: led,raspberrypi
Classifier: License :: OSI Approved :: MIT License
Classifier: Operating System :: OS Independent
Classifier: Programming Language :: Python
Classifier: Programming Language :: Python :: 3
Classifier: Programming Language :: Python :: 3.8
Classifier: Programming Language :: Python :: 3.9
Classifier: Programming Language :: Python :: 3 :: Only
License-File: LICENSE
Requires-Dist: click
Requires-Dist: pysolar
Requires-Dist: gpiozero
Requires-Dist: pigpio
